hedra/__init__.py
hedra/cli/__init__.py
hedra/cli/base.py
hedra/cli/cloud.py
hedra/cli/graph.py
hedra/cli/ping.py
hedra/cli/plugin.py
hedra/cli/project.py
hedra/cli/cloud/__init__.py
hedra/cli/cloud/check.py
hedra/cli/cloud/login.py
hedra/cli/cloud/run.py
hedra/cli/cloud/submit.py
hedra/cli/cloud/sync.py
hedra/cli/cloud/update.py
hedra/cli/cloud/watch.py
hedra/cli/exceptions/__init__.py
hedra/cli/exceptions/graph/__init__.py
hedra/cli/exceptions/graph/create/__init__.py
hedra/cli/exceptions/graph/create/invalid_stage_type.py
hedra/cli/exceptions/graph/sync/__init__.py
hedra/cli/exceptions/graph/sync/not_set_error.py
hedra/cli/exceptions/plugin/__init__.py
hedra/cli/exceptions/plugin/create/__init__.py
hedra/cli/exceptions/plugin/create/invaid_plugin_type.py
hedra/cli/graph/__init__.py
hedra/cli/graph/check.py
hedra/cli/graph/create.py
hedra/cli/graph/run.py
hedra/cli/plugin/__init__.py
hedra/cli/plugin/create.py
hedra/cli/project/__init__.py
hedra/cli/project/about.py
hedra/cli/project/create.py
hedra/cli/project/get.py
hedra/cli/project/sync.py
hedra/core/__init__.py
hedra/core/engines/__init__.py
hedra/core/engines/client/__init__.py
hedra/core/engines/client/client.py
hedra/core/engines/client/config.py
hedra/core/engines/client/plugins_store.py
hedra/core/engines/client/store.py
hedra/core/engines/client/time_parser.py
hedra/core/engines/client/tracing_config.py
hedra/core/engines/client/client_types/__init__.py
hedra/core/engines/client/client_types/base_client.py
hedra/core/engines/client/client_types/graphql.py
hedra/core/engines/client/client_types/graphql_http2.py
hedra/core/engines/client/client_types/grpc.py
hedra/core/engines/client/client_types/http.py
hedra/core/engines/client/client_types/http2.py
hedra/core/engines/client/client_types/http3.py
hedra/core/engines/client/client_types/playwright.py
hedra/core/engines/client/client_types/task.py
hedra/core/engines/client/client_types/udp.py
hedra/core/engines/client/client_types/websocket.py
hedra-0.7.24.dist-info/LICENSE
hedra-0.7.24.dist-info/METADATA
hedra-0.7.24.dist-info/WHEEL
hedra-0.7.24.dist-info/entry_points.txt
hedra-0.7.24.dist-info/top_level.txt
hedra-0.7.24.dist-info/RECORD
