Metadata-Version: 2.1
Name: hedra
Version: 0.7.24
Summary: Performance testing at scale.
Author-email: Ada Lundhe <sean.corbett@umconnect.edu>
License: MIT License
Project-URL: Homepage, https://github.com/adalundhe/hedra
Keywords: pypi,cicd,python,performance,testing,dag,graph,workflow
Classifier: Programming Language :: Python :: 3.8
Classifier: Programming Language :: Python :: 3.9
Classifier: Programming Language :: Python :: 3.10
Classifier: Programming Language :: Python :: 3.11
Classifier: License :: OSI Approved :: MIT License
Classifier: Operating System :: OS Independent
Requires-Python: >=3.10
License-File: LICENSE
Requires-Dist: hyperframe
Requires-Dist: aiologger
Requires-Dist: yaspin
Requires-Dist: attr
Requires-Dist: networkx
Requires-Dist: aiodns
Requires-Dist: click
Requires-Dist: psutil
Requires-Dist: fastapi
Requires-Dist: dill
Requires-Dist: scipy
Requires-Dist: art
Requires-Dist: scikit-learn
Requires-Dist: uvloop
Requires-Dist: tdigest
Requires-Dist: pydantic
Requires-Dist: GitPython
Requires-Dist: tabulate
Requires-Dist: plotille
Requires-Dist: python3-dtls
Requires-Dist: zstandard
Requires-Dist: cryptography
Requires-Dist: python-dotenv
Provides-Extra: all
Requires-Dist: grpcio; extra == "all"
Requires-Dist: grpcio-tools; extra == "all"
Requires-Dist: gql; extra == "all"
Requires-Dist: playwright; extra == "all"
Requires-Dist: azure-cosmos; extra == "all"
Requires-Dist: libhoney; extra == "all"
Requires-Dist: influxdb-client; extra == "all"
Requires-Dist: newrelic; extra == "all"
Requires-Dist: aio-statsd; extra == "all"
Requires-Dist: prometheus-client; extra == "all"
Requires-Dist: prometheus-api-client; extra == "all"
Requires-Dist: cassandra-driver; extra == "all"
Requires-Dist: datadog; extra == "all"
Requires-Dist: motor; extra == "all"
Requires-Dist: redis; extra == "all"
Requires-Dist: aioredis; extra == "all"
Requires-Dist: aiomysql; extra == "all"
Requires-Dist: psycopg2-binary; extra == "all"
Requires-Dist: sqlalchemy; extra == "all"
Requires-Dist: sqlalchemy[asyncio]; extra == "all"
Requires-Dist: boto3; extra == "all"
Requires-Dist: snowflake-sqlalchemy; extra == "all"
Requires-Dist: snowflake-connector-python; extra == "all"
Requires-Dist: google-cloud-bigquery; extra == "all"
Requires-Dist: google-cloud-bigtable; extra == "all"
Requires-Dist: google-cloud-storage; extra == "all"
Requires-Dist: cryptography==38.0.4; extra == "all"
Requires-Dist: aioquic; extra == "all"
Requires-Dist: dicttoxml; extra == "all"
Requires-Dist: opentelemetry-api; extra == "all"
Requires-Dist: datadog-api-client; extra == "all"
Requires-Dist: aiokafka; extra == "all"
Requires-Dist: haralyzer; extra == "all"
Requires-Dist: asyncpg; extra == "all"
Requires-Dist: xmltodict; extra == "all"
Provides-Extra: all-engines
Requires-Dist: grpcio; extra == "all-engines"
Requires-Dist: grpcio-tools; extra == "all-engines"
Requires-Dist: gql; extra == "all-engines"
Requires-Dist: playwright; extra == "all-engines"
Requires-Dist: cryptography==38.0.4; extra == "all-engines"
Requires-Dist: aioquic; extra == "all-engines"
Requires-Dist: opentelemetry-api; extra == "all-engines"
Provides-Extra: all-reporters
Requires-Dist: azure-cosmos; extra == "all-reporters"
Requires-Dist: libhoney; extra == "all-reporters"
Requires-Dist: influxdb-client; extra == "all-reporters"
Requires-Dist: newrelic; extra == "all-reporters"
Requires-Dist: aio-statsd; extra == "all-reporters"
Requires-Dist: prometheus-client; extra == "all-reporters"
Requires-Dist: prometheus-api-client; extra == "all-reporters"
Requires-Dist: cassandra-driver; extra == "all-reporters"
Requires-Dist: datadog; extra == "all-reporters"
Requires-Dist: motor; extra == "all-reporters"
Requires-Dist: redis; extra == "all-reporters"
Requires-Dist: aioredis; extra == "all-reporters"
Requires-Dist: aiomysql; extra == "all-reporters"
Requires-Dist: psycopg2-binary; extra == "all-reporters"
Requires-Dist: asyncpg; extra == "all-reporters"
Requires-Dist: sqlalchemy; extra == "all-reporters"
Requires-Dist: boto3; extra == "all-reporters"
Requires-Dist: snowflake-connector-python; extra == "all-reporters"
Requires-Dist: google-cloud-bigquery; extra == "all-reporters"
Requires-Dist: google-cloud-bigtable; extra == "all-reporters"
Requires-Dist: google-cloud-storage; extra == "all-reporters"
Requires-Dist: dicttoxml; extra == "all-reporters"
Requires-Dist: datadog-api-client; extra == "all-reporters"
Requires-Dist: aiosonic; extra == "all-reporters"
Requires-Dist: aiokafka; extra == "all-reporters"
Provides-Extra: aws
Requires-Dist: boto3; extra == "aws"
Provides-Extra: azure
Requires-Dist: azure-cosmos; extra == "azure"
Provides-Extra: cassandra
Requires-Dist: cassandra-driver; extra == "cassandra"
Provides-Extra: datadog
Requires-Dist: datadog-api-client; extra == "datadog"
Requires-Dist: aiosonic; extra == "datadog"
Provides-Extra: google
Requires-Dist: google-cloud-bigquery; extra == "google"
Requires-Dist: google-cloud-bigtable; extra == "google"
Requires-Dist: google-cloud-storage; extra == "google"
Provides-Extra: graphql
Requires-Dist: gql; extra == "graphql"
Provides-Extra: grpc
Requires-Dist: grpcio; extra == "grpc"
Requires-Dist: grpcio-tools; extra == "grpc"
Provides-Extra: har
Requires-Dist: haralyzer; extra == "har"
Provides-Extra: honeycomb
Requires-Dist: libhoney; extra == "honeycomb"
Provides-Extra: http3
Requires-Dist: cryptography==38.0.4; extra == "http3"
Requires-Dist: aioquic; extra == "http3"
Provides-Extra: influxdb
Requires-Dist: influxdb-client; extra == "influxdb"
Provides-Extra: kafka
Requires-Dist: aiokafka; extra == "kafka"
Provides-Extra: mongodb
Requires-Dist: motor; extra == "mongodb"
Provides-Extra: newrelic
Requires-Dist: newrelic; extra == "newrelic"
Provides-Extra: opentelemetry
Requires-Dist: opentelemetry-api; extra == "opentelemetry"
Provides-Extra: playwright
Requires-Dist: playwright; extra == "playwright"
Provides-Extra: prometheus
Requires-Dist: prometheus-client; extra == "prometheus"
Requires-Dist: prometheus-api-client; extra == "prometheus"
Provides-Extra: redis
Requires-Dist: redis; extra == "redis"
Requires-Dist: aioredis; extra == "redis"
Provides-Extra: snowflake
Requires-Dist: snowflake-sqlalchemy; extra == "snowflake"
Requires-Dist: snowflake-connector-python; extra == "snowflake"
Provides-Extra: sql
Requires-Dist: aiomysql; extra == "sql"
Requires-Dist: psycopg2-binary; extra == "sql"
Requires-Dist: asyncpg; extra == "sql"
Requires-Dist: sqlalchemy; extra == "sql"
Requires-Dist: sqlalchemy[asyncio]; extra == "sql"
Provides-Extra: statsd
Requires-Dist: aio-statsd; extra == "statsd"
Provides-Extra: xml
Requires-Dist: dicttoxml; extra == "xml"
Requires-Dist: xmltodict; extra == "xml"
